pyPRUF/__init__.py
pyPRUF/fuzzy_logic.py
pyPRUF/fuzzy_sets.py
pyPRUF/membership_functions.py
pyPRUF-0.0.3.dist-info/LICENSE.txt
pyPRUF-0.0.3.dist-info/METADATA
pyPRUF-0.0.3.dist-info/WHEEL
pyPRUF-0.0.3.dist-info/top_level.txt
pyPRUF-0.0.3.dist-info/RECORD
