Metadata-Version: 2.2
Name: pyPRUF
Version: 0.0.3
Summary: A Python library for PRUF, a meaning representation and manipulation language for approximate reasoning purposes, proposed by Zadeh.
Author: Nicolò Resta
Author-email: nicoloresta02@gmail.com
Project-URL: Documentation, https://readthedocs.org
Project-URL: Repository, https://github.com/ashkihotah/pyPRUF
Keywords: AI,XAI,PRUF,fuzzy relations,fuzzy logic,fuzzy sets,possibilistic logic,approximate reasoning,fuzzy relational algebra
Requires-Python: >=3.11
License-File: LICENSE.txt
Requires-Dist: pandas
